odoo/addons/shopinvader_delivery_carrier/README.rst
odoo/addons/shopinvader_delivery_carrier/__init__.py
odoo/addons/shopinvader_delivery_carrier/__manifest__.py
odoo/addons/shopinvader_delivery_carrier/i18n/shopinvader_delivery_carrier.pot
odoo/addons/shopinvader_delivery_carrier/models/__init__.py
odoo/addons/shopinvader_delivery_carrier/models/delivery_carrier.py
odoo/addons/shopinvader_delivery_carrier/models/sale_order.py
odoo/addons/shopinvader_delivery_carrier/readme/CONTRIBUTORS.rst
odoo/addons/shopinvader_delivery_carrier/readme/DESCRIPTION.rst
odoo/addons/shopinvader_delivery_carrier/static/description/index.html
odoo_addon_shopinvader_delivery_carrier-16.0.1.0.0.3.dist-info/METADATA
odoo_addon_shopinvader_delivery_carrier-16.0.1.0.0.3.dist-info/WHEEL
odoo_addon_shopinvader_delivery_carrier-16.0.1.0.0.3.dist-info/top_level.txt
odoo_addon_shopinvader_delivery_carrier-16.0.1.0.0.3.dist-info/RECORD
