Metadata-Version: 2.1
Name: odoo-addon-shopinvader-delivery-carrier
Version: 16.0.1.0.0.3
Summary: ShopInvader logic for delivery carriers.
Home-page: https://github.com/shopinvader/odoo-shopinvader-carrier
Author: ACSONE SA/NV,Shopinvader
License: AGPL-3
Platform: UNKNOWN
Classifier: Programming Language :: Python
Classifier: Framework :: Odoo
Classifier: Framework :: Odoo :: 16.0
Classifier: License :: OSI Approved :: GNU Affero General Public License v3
Requires-Python: >=3.10
Requires-Dist: odoo <16.1dev,>=16.0a
